Workbook

Sheet README
A1: Lab 10 -- Growth Projection Template
A3: How to use this template:
A5: 1. Open the Inputs tab. Choose your scenario in cell B3 (Best, Expected, or Worst).
A6: 2. Fill in the yellow cells with your team's assumptions for each of the three channels.
A7: 3. Every yellow cell needs a source. Add a comment with the source for each.
A8: 4. Open the Calculations tab. Do NOT edit -- all values are formulas.
A9: 5. Open the Output tab. Review the cumulative users chart and the summary table.
A10: 6. Switch the scenario in B3 of Inputs to see Best / Expected / Worst.
A11: 7. Save the file as growth-projection.xlsx and commit to 04-gtm/financials/
A13: Color conventions used in this workbook:
A14: Blue text = hardcoded input you can change
A15: Black text = formula (do not edit directly)
... A22: Submission: commit growth-projection.xlsx to 04-gtm/financials/ before end of lab.

Sheet Inputs
A1: TutorLink — Growth Projection Inputs
A3: Active scenario (type: Best / Expected / Worst) | B3: Expected | C3: ← Change to switch scenario in Calculations
A5: General Assumptions
A6: Projection period (months) | B6: 12
A7: Month 1 start date | B7: May 2026
A8: Blended gross margin (%) | B8: 0.8
A9: Average lifetime (months) | B9: 18
A10: Monthly churn rate (%) | B10: 0.05
A12: Channel 1 — KIU International Student Office
A13: Assumption | B13: Worst | C13: Expected | D13: Best | E13: Source / Note
A14: Outreach contacts (students) | B14: 20 | C14: 40 | D14: 60
A15: Landing page visit rate (%) | B15: 0.4 | C15: 0.6 | D15: 0.8
A16: Signup conversion rate (%) | B16: 0.15 | C16: 0.25 | D16: 0.4
A17: Monthly new users from this channel | B17: =B14*B15*B16 -> 1.2 | C17: =C14*C15*C16 -> 6 | D17: =D14*D15*D16 -> 19.2
A18: Month-over-month growth rate (%) | B18: 0.05 | C18: 0.1 | D18: 0.2
A20: Channel 2 — University WhatsApp & Messenger Group Chats
A21: Assumption | B21: Worst | C21: Expected | D21: Best | E21: Source / Note
A22: Group chat posts per month (team total) | B22: 4 | C22: 8 | D22: 12
A23: Average reach per post (students) | B23: 80 | C23: 150 | D23: 250
A24: Click-through rate on post (%) | B24: 0.05 | C24: 0.12 | D24: 0.2
A25: Signup conversion from click (%) | B25: 0.2 | C25: 0.3 | D25: 0.45
A26: Monthly new users from this channel | B26: =B22*B23*B24*B25 -> 3.2 | C26: =C22*C23*C24*C25 -> 43.2 | D26: =D22*D23*D24*D25 -> 270
A27: Month-over-month growth rate (%) | B27: 0 | C27: 0.05 | D27: 0.1
A29: Channel 3 — Tutor-Side Word of Mouth (Profile Sharing)
A30: Assumption | B30: Worst | C30: Expected | D30: Best | E30: Source / Note
A31: Active tutors on platform (by end Sprint 2) | B31: 5 | C31: 15 | D31: 25
A32: Students referred per tutor per month | B32: 1 | C32: 3 | D32: 5
A33: Signup conversion from tutor referral (%) | B33: 0.25 | C33: 0.4 | D33: 0.6
A34: Monthly new users from this channel | B34: =B31*B32*B33 -> 1.25 | C34: =C31*C32*C33 -> 18 | D34: =D31*D32*D33 -> 75
A35: Month-over-month growth rate (%) | B35: 0.05 | C35: 0.15 | D35: 0.25
A37: Unit Economics Assumptions
A38: Assumption | B38: Worst | C38: Expected | D38: Best | E38: Source / Note
A39: Tutor featured plan price (GEL/month) | B39: 15 | C39: 30 | D39: 50
A40: % of active tutors on paid plan | B40: 0.1 | C40: 0.25 | D40: 0.4
A41: ARPU - students (GEL/month, proxy value) | B41: 0 | C41: 0 | D41: 0
A42: CAC - Ch1 International Office (GEL) | B42: 10 | C42: 5 | D42: 2
A43: CAC - Ch2 WhatsApp Group Chats (GEL) | B43: 8 | C43: 3 | D43: 1
A44: CAC - Ch3 Tutor Word of Mouth (GEL) | B44: 5 | C44: 2 | D44: 0.5

Sheet Calculations
A1: TutorLink — Growth Calculations (DO NOT EDIT — all formulas)
A3: Active scenario (from Inputs!B3): | B3: =Inputs!B3 -> Expected
A5: Metric | B5: May 2026 | C5: Jun 2026 | D5: Jul 2026 | E5: Aug 2026 | F5: Sep 2026 | G5: Oct 2026 | H5: Nov 2026 | I5: Dec 2026 | J5: Jan 2027 | K5: Feb 2027 | L5: Mar 2027 | M5: Apr 2027 | N5: 12-Mo Total
A7: Channel 1 — KIU International Student Office
A8: New users this month | B8: =CHOOSE(MATCH(Inputs!B3,{"Worst","Expected","Best"},0),Inputs!B17,Inputs!C17,Inputs!D17) -> 6 | C8: =CHOOSE(MATCH(Inputs!B3,{"Worst","Expected","Best"},0),B8*(1+Inputs!B18),B8*(1+Inputs!C18),B8*(1+Inputs!D18)) -> 6.6 | D8: =CHOOSE(MATCH(Inputs!B3,{"Worst","Expected","Best"},0),C8*(1+Inputs!B18),C8*(1+Inputs!C18),C8*(1+Inputs!D18)) -> 7.26 | E8: =CHOOSE(MATCH(Inputs!B3,{"Worst","Expected","Best"},0),D8*(1+Inputs!B18),D8*(1+Inputs!C18),D8*(1+Inputs!D18)) -> 7.986 | F8: =CHOOSE(MATCH(Inputs!B3,{"Worst","Expected","Best"},0),E8*(1+Inputs!B18),E8*(1+Inputs!C18),E8*(1+Inputs!D18)) -> 8.7846 | G8: =CHOOSE(MATCH(Inputs!B3,{"Worst","Expected","Best"},0),F8*(1+Inputs!B18),F8*(1+Inputs!C18),F8*(1+Inputs!D18)) -> 9.66306 | H8: =CHOOSE(MATCH(Inputs!B3,{"Worst","Expected","Best"},0),G8*(1+Inputs!B18),G8*(1+Inputs!C18),G8*(1+Inputs!D18)) -> 10.629366 | I8: =CHOOSE(MATCH(Inputs!B3,{"Worst","Expected","Best"},0),H8*(1+Inputs!B18),H8*(1+Inputs!C18),H8*(1+Inputs!D18)) -> 11.692303 | J8: =CHOOSE(MATCH(Inputs!B3,{"Worst","Expected","Best"},0),I8*(1+Inputs!B18),I8*(1+Inputs!C18),I8*(1+Inputs!D18)) -> 12.861533 | K8: =CHOOSE(MATCH(Inputs!B3,{"Worst","Expected","Best"},0),J8*(1+Inputs!B18),J8*(1+Inputs!C18),J8*(1+Inputs!D18)) -> 14.147686 | L8: =CHOOSE(MATCH(Inputs!B3,{"Worst","Expected","Best"},0),K8*(1+Inputs!B18),K8*(1+Inputs!C18),K8*(1+Inputs!D18)) -> 15.562455 | M8: =CHOOSE(MATCH(Inputs!B3,{"Worst","Expected","Best"},0),L8*(1+Inputs!B18),L8*(1+Inputs!C18),L8*(1+Inputs!D18)) -> 17.1187 | N8: =SUM(B8:M8) -> 128.3057
A9: Cumulative users | B9: =B8 -> 6 | C9: =B9+C8 -> 12.6 | D9: =C9+D8 -> 19.86 | E9: =D9+E8 -> 27.846 | F9: =E9+F8 -> 36.6306 | G9: =F9+G8 -> 46.29366 | H9: =G9+H8 -> 56.923026 | I9: =H9+I8 -> 68.615329 | J9: =I9+J8 -> 81.476861 | ... M9: =L9+M8 -> 128.3057 | N9: =M9 -> 128.3057
A10: Churned users (monthly) | B10: =0 -> 0 | C10: =B11*Inputs!C10 -> 0 | D10: =C11*Inputs!C10 -> 0 | E10: =D11*Inputs!C10 -> 0 | F10: =E11*Inputs!C10 -> 0 | G10: =F11*Inputs!C10 -> 0 | H10: =G11*Inputs!C10 -> 0 | I10: =H11*Inputs!C10 -> 0 | J10: =I11*Inputs!C10 -> 0 | K10: =J11*Inputs!C10 -> 0 | L10: =K11*Inputs!C10 -> 0 | M10: =L11*Inputs!C10 -> 0 | N10: =SUM(B10:M10) -> 0
A11: Net active users | B11: =B8-B10 -> 6 | C11: =B11+C8-C10 -> 12.6 | D11: =C11+D8-D10 -> 19.86 | E11: =D11+E8-E10 -> 27.846 | F11: =E11+F8-F10 -> 36.6306 | G11: =F11+G8-G10 -> 46.29366 | H11: =G11+H8-H10 -> 56.923026 | I11: =H11+I8-I10 -> 68.615329 | J11: =I11+J8-J10 -> 81.476861 | ... M11: =L11+M8-M10 -> 128.3057 | N11: =M11 -> 128.3057
A14: Channel 2 — WhatsApp / Messenger Group Chats
A15: New users this month | B15: =CHOOSE(MATCH(Inputs!B3,{"Worst","Expected","Best"},0),Inputs!B26,Inputs!C26,Inputs!D26) -> 43.2 | C15: =CHOOSE(MATCH(Inputs!B3,{"Worst","Expected","Best"},0),B15*(1+Inputs!B27),B15*(1+Inputs!C27),B15*(1+Inputs!D27)) -> 45.36 | D15: =CHOOSE(MATCH(Inputs!B3,{"Worst","Expected","Best"},0),C15*(1+Inputs!B27),C15*(1+Inputs!C27),C15*(1+Inputs!D27)) -> 47.628 | E15: =CHOOSE(MATCH(Inputs!B3,{"Worst","Expected","Best"},0),D15*(1+Inputs!B27),D15*(1+Inputs!C27),D15*(1+Inputs!D27)) -> 50.0094 | F15: =CHOOSE(MATCH(Inputs!B3,{"Worst","Expected","Best"},0),E15*(1+Inputs!B27),E15*(1+Inputs!C27),E15*(1+Inputs!D27)) -> 52.50987 | G15: =CHOOSE(MATCH(Inputs!B3,{"Worst","Expected","Best"},0),F15*(1+Inputs!B27),F15*(1+Inputs!C27),F15*(1+Inputs!D27)) -> 55.135363 | H15: =CHOOSE(MATCH(Inputs!B3,{"Worst","Expected","Best"},0),G15*(1+Inputs!B27),G15*(1+Inputs!C27),G15*(1+Inputs!D27)) -> 57.892132 | I15: =CHOOSE(MATCH(Inputs!B3,{"Worst","Expected","Best"},0),H15*(1+Inputs!B27),H15*(1+Inputs!C27),H15*(1+Inputs!D27)) -> 60.786738 | J15: =CHOOSE(MATCH(Inputs!B3,{"Worst","Expected","Best"},0),I15*(1+Inputs!B27),I15*(1+Inputs!C27),I15*(1+Inputs!D27)) -> 63.826075 | K15: =CHOOSE(MATCH(Inputs!B3,{"Worst","Expected","Best"},0),J15*(1+Inputs!B27),J15*(1+Inputs!C27),J15*(1+Inputs!D27)) -> 67.017379 | L15: =CHOOSE(MATCH(Inputs!B3,{"Worst","Expected","Best"},0),K15*(1+Inputs!B27),K15*(1+Inputs!C27),K15*(1+Inputs!D27)) -> 70.368248 | M15: =CHOOSE(MATCH(Inputs!B3,{"Worst","Expected","Best"},0),L15*(1+Inputs!B27),L15*(1+Inputs!C27),L15*(1+Inputs!D27)) -> 73.88666 | N15: =SUM(B15:M15) -> 687.61987
A16: Cumulative users | B16: =B15 -> 43.2 | C16: =B16+C15 -> 88.56 | D16: =C16+D15 -> 136.188 | E16: =D16+E15 -> 186.1974 | F16: =E16+F15 -> 238.70727 | G16: =F16+G15 -> 293.84263 | H16: =G16+H15 -> 351.73477 | I16: =H16+I15 -> 412.5215 | J16: =I16+J15 -> 476.34758 | ... M16: =L16+M15 -> 687.61987 | N16: =M16 -> 687.61987
A17: Churned users (monthly) | B17: =0 -> 0 | C17: =B18*Inputs!C10 -> 0 | D17: =C18*Inputs!C10 -> 0 | E17: =D18*Inputs!C10 -> 0 | F17: =E18*Inputs!C10 -> 0 | G17: =F18*Inputs!C10 -> 0 | H17: =G18*Inputs!C10 -> 0 | I17: =H18*Inputs!C10 -> 0 | J17: =I18*Inputs!C10 -> 0 | K17: =J18*Inputs!C10 -> 0 | L17: =K18*Inputs!C10 -> 0 | M17: =L18*Inputs!C10 -> 0 | N17: =SUM(B17:M17) -> 0
A18: Net active users | B18: =B15-B17 -> 43.2 | C18: =B18+C15-C17 -> 88.56 | D18: =C18+D15-D17 -> 136.188 | E18: =D18+E15-E17 -> 186.1974 | F18: =E18+F15-F17 -> 238.70727 | G18: =F18+G15-G17 -> 293.84263 | H18: =G18+H15-H17 -> 351.73477 | I18: =H18+I15-I17 -> 412.5215 | J18: =I18+J15-J17 -> 476.34758 | ... M18: =L18+M15-M17 -> 687.61987 | N18: =M18 -> 687.61987
A21: Channel 3 — Tutor-Side Word of Mouth
A22: New users this month | B22: =CHOOSE(MATCH(Inputs!B3,{"Worst","Expected","Best"},0),Inputs!B34,Inputs!C34,Inputs!D34) -> 18 | C22: =CHOOSE(MATCH(Inputs!B3,{"Worst","Expected","Best"},0),B22*(1+Inputs!B35),B22*(1+Inputs!C35),B22*(1+Inputs!D35)) -> 20.7 | D22: =CHOOSE(MATCH(Inputs!B3,{"Worst","Expected","Best"},0),C22*(1+Inputs!B35),C22*(1+Inputs!C35),C22*(1+Inputs!D35)) -> 23.805 | E22: =CHOOSE(MATCH(Inputs!B3,{"Worst","Expected","Best"},0),D22*(1+Inputs!B35),D22*(1+Inputs!C35),D22*(1+Inputs!D35)) -> 27.37575 | F22: =CHOOSE(MATCH(Inputs!B3,{"Worst","Expected","Best"},0),E22*(1+Inputs!B35),E22*(1+Inputs!C35),E22*(1+Inputs!D35)) -> 31.482112 | G22: =CHOOSE(MATCH(Inputs!B3,{"Worst","Expected","Best"},0),F22*(1+Inputs!B35),F22*(1+Inputs!C35),F22*(1+Inputs!D35)) -> 36.204429 | H22: =CHOOSE(MATCH(Inputs!B3,{"Worst","Expected","Best"},0),G22*(1+Inputs!B35),G22*(1+Inputs!C35),G22*(1+Inputs!D35)) -> 41.635094 | I22: =CHOOSE(MATCH(Inputs!B3,{"Worst","Expected","Best"},0),H22*(1+Inputs!B35),H22*(1+Inputs!C35),H22*(1+Inputs!D35)) -> 47.880358 | J22: =CHOOSE(MATCH(Inputs!B3,{"Worst","Expected","Best"},0),I22*(1+Inputs!B35),I22*(1+Inputs!C35),I22*(1+Inputs!D35)) -> 55.062412 | K22: =CHOOSE(MATCH(Inputs!B3,{"Worst","Expected","Best"},0),J22*(1+Inputs!B35),J22*(1+Inputs!C35),J22*(1+Inputs!D35)) -> 63.321773 | L22: =CHOOSE(MATCH(Inputs!B3,{"Worst","Expected","Best"},0),K22*(1+Inputs!B35),K22*(1+Inputs!C35),K22*(1+Inputs!D35)) -> 72.820039 | M22: =CHOOSE(MATCH(Inputs!B3,{"Worst","Expected","Best"},0),L22*(1+Inputs!B35),L22*(1+Inputs!C35),L22*(1+Inputs!D35)) -> 83.743045 | N22: =SUM(B22:M22) -> 522.03001
A23: Cumulative users | B23: =B22 -> 18 | C23: =B23+C22 -> 38.7 | D23: =C23+D22 -> 62.505 | E23: =D23+E22 -> 89.88075 | F23: =E23+F22 -> 121.36286 | G23: =F23+G22 -> 157.56729 | H23: =G23+H22 -> 199.20239 | I23: =H23+I22 -> 247.08274 | J23: =I23+J22 -> 302.14516 | ... M23: =L23+M22 -> 522.03001 | N23: =M23 -> 522.03001
A24: Churned users (monthly) | B24: =0 -> 0 | C24: =B25*Inputs!C10 -> 0 | D24: =C25*Inputs!C10 -> 0 | E24: =D25*Inputs!C10 -> 0 | F24: =E25*Inputs!C10 -> 0 | G24: =F25*Inputs!C10 -> 0 | H24: =G25*Inputs!C10 -> 0 | I24: =H25*Inputs!C10 -> 0 | J24: =I25*Inputs!C10 -> 0 | K24: =J25*Inputs!C10 -> 0 | L24: =K25*Inputs!C10 -> 0 | M24: =L25*Inputs!C10 -> 0 | N24: =SUM(B24:M24) -> 0
A25: Net active users | B25: =B22-B24 -> 18 | C25: =B25+C22-C24 -> 38.7 | D25: =C25+D22-D24 -> 62.505 | E25: =D25+E22-E24 -> 89.88075 | F25: =E25+F22-F24 -> 121.36286 | G25: =F25+G22-G24 -> 157.56729 | H25: =G25+H22-H24 -> 199.20239 | I25: =H25+I22-I24 -> 247.08274 | J25: =I25+J22-J24 -> 302.14516 | ... M25: =L25+M22-M24 -> 522.03001 | N25: =M25 -> 522.03001
A28: Combined — All Channels
A29: Total new users (all channels) | B29: =SUM(B8,B15,B22) -> 67.2 | C29: =SUM(C8,C15,C22) -> 72.66 | D29: =SUM(D8,D15,D22) -> 78.693 | E29: =SUM(E8,E15,E22) -> 85.37115 | F29: =SUM(F8,F15,F22) -> 92.776583 | G29: =SUM(G8,G15,G22) -> 101.00285 | H29: =SUM(H8,H15,H22) -> 110.15659 | I29: =SUM(I8,I15,I22) -> 120.3594 | ... M29: =SUM(M8,M15,M22) -> 174.74841 | N29: =SUM(B29:M29) -> 1337.9556
A30: Total net active users | B30: =SUM(B11,B18,B25) -> 67.2 | C30: =SUM(C11,C18,C25) -> 139.86 | D30: =SUM(D11,D18,D25) -> 218.553 | E30: =SUM(E11,E18,E25) -> 303.92415 | F30: =SUM(F11,F18,F25) -> 396.70073 | G30: =SUM(G11,G18,G25) -> 497.70359 | H30: =SUM(H11,H18,H25) -> 607.86018 | I30: =SUM(I11,I18,I25) -> 728.21958 | ... M30: =SUM(M11,M18,M25) -> 1337.9556 | N30: =M30 -> 1337.9556
A31: Total active tutors (scenario) | B31: =CHOOSE(MATCH(Inputs!B3,{"Worst","Expected","Best"},0),Inputs!B31,Inputs!C31,Inputs!D31) -> 15 | C31: =CHOOSE(MATCH(Inputs!B3,{"Worst","Expected","Best"},0),B31*(1+Inputs!B35),B31*(1+Inputs!C35),B31*(1+Inputs!D35)) -> 17.25 | D31: =CHOOSE(MATCH(Inputs!B3,{"Worst","Expected","Best"},0),C31*(1+Inputs!B35),C31*(1+Inputs!C35),C31*(1+Inputs!D35)) -> 19.8375 | E31: =CHOOSE(MATCH(Inputs!B3,{"Worst","Expected","Best"},0),D31*(1+Inputs!B35),D31*(1+Inputs!C35),D31*(1+Inputs!D35)) -> 22.813125 | F31: =CHOOSE(MATCH(Inputs!B3,{"Worst","Expected","Best"},0),E31*(1+Inputs!B35),E31*(1+Inputs!C35),E31*(1+Inputs!D35)) -> 26.235094 | G31: =CHOOSE(MATCH(Inputs!B3,{"Worst","Expected","Best"},0),F31*(1+Inputs!B35),F31*(1+Inputs!C35),F31*(1+Inputs!D35)) -> 30.170358 | H31: =CHOOSE(MATCH(Inputs!B3,{"Worst","Expected","Best"},0),G31*(1+Inputs!B35),G31*(1+Inputs!C35),G31*(1+Inputs!D35)) -> 34.695911 | I31: =CHOOSE(MATCH(Inputs!B3,{"Worst","Expected","Best"},0),H31*(1+Inputs!B35),H31*(1+Inputs!C35),H31*(1+Inputs!D35)) -> 39.900298 | J31: =CHOOSE(MATCH(Inputs!B3,{"Worst","Expected","Best"},0),I31*(1+Inputs!B35),I31*(1+Inputs!C35),I31*(1+Inputs!D35)) -> 45.885343 | K31: =CHOOSE(MATCH(Inputs!B3,{"Worst","Expected","Best"},0),J31*(1+Inputs!B35),J31*(1+Inputs!C35),J31*(1+Inputs!D35)) -> 52.768144 | L31: =CHOOSE(MATCH(Inputs!B3,{"Worst","Expected","Best"},0),K31*(1+Inputs!B35),K31*(1+Inputs!C35),K31*(1+Inputs!D35)) -> 60.683366 | M31: =CHOOSE(MATCH(Inputs!B3,{"Worst","Expected","Best"},0),L31*(1+Inputs!B35),L31*(1+Inputs!C35),L31*(1+Inputs!D35)) -> 69.785871 | N31: =M31 -> 69.785871
A32: Tutors on paid plan | B32: =CHOOSE(MATCH(Inputs!B3,{"Worst","Expected","Best"},0),B31*Inputs!B40,B31*Inputs!C40,B31*Inputs!D40) -> 3.75 | C32: =CHOOSE(MATCH(Inputs!B3,{"Worst","Expected","Best"},0),C31*Inputs!B40,C31*Inputs!C40,C31*Inputs!D40) -> 4.3125 | D32: =CHOOSE(MATCH(Inputs!B3,{"Worst","Expected","Best"},0),D31*Inputs!B40,D31*Inputs!C40,D31*Inputs!D40) -> 4.959375 | E32: =CHOOSE(MATCH(Inputs!B3,{"Worst","Expected","Best"},0),E31*Inputs!B40,E31*Inputs!C40,E31*Inputs!D40) -> 5.7032812 | F32: =CHOOSE(MATCH(Inputs!B3,{"Worst","Expected","Best"},0),F31*Inputs!B40,F31*Inputs!C40,F31*Inputs!D40) -> 6.5587734 | G32: =CHOOSE(MATCH(Inputs!B3,{"Worst","Expected","Best"},0),G31*Inputs!B40,G31*Inputs!C40,G31*Inputs!D40) -> 7.5425895 | H32: =CHOOSE(MATCH(Inputs!B3,{"Worst","Expected","Best"},0),H31*Inputs!B40,H31*Inputs!C40,H31*Inputs!D40) -> 8.6739779 | I32: =CHOOSE(MATCH(Inputs!B3,{"Worst","Expected","Best"},0),I31*Inputs!B40,I31*Inputs!C40,I31*Inputs!D40) -> 9.9750746 | J32: =CHOOSE(MATCH(Inputs!B3,{"Worst","Expected","Best"},0),J31*Inputs!B40,J31*Inputs!C40,J31*Inputs!D40) -> 11.471336 | K32: =CHOOSE(MATCH(Inputs!B3,{"Worst","Expected","Best"},0),K31*Inputs!B40,K31*Inputs!C40,K31*Inputs!D40) -> 13.192036 | L32: =CHOOSE(MATCH(Inputs!B3,{"Worst","Expected","Best"},0),L31*Inputs!B40,L31*Inputs!C40,L31*Inputs!D40) -> 15.170842 | M32: =CHOOSE(MATCH(Inputs!B3,{"Worst","Expected","Best"},0),M31*Inputs!B40,M31*Inputs!C40,M31*Inputs!D40) -> 17.446468 | N32: =M32 -> 17.446468
A33: Monthly revenue (GEL) | B33: =CHOOSE(MATCH(Inputs!B3,{"Worst","Expected","Best"},0),B32*Inputs!B39,B32*Inputs!C39,B32*Inputs!D39) -> 112.5 | C33: =CHOOSE(MATCH(Inputs!B3,{"Worst","Expected","Best"},0),C32*Inputs!B39,C32*Inputs!C39,C32*Inputs!D39) -> 129.375 | D33: =CHOOSE(MATCH(Inputs!B3,{"Worst","Expected","Best"},0),D32*Inputs!B39,D32*Inputs!C39,D32*Inputs!D39) -> 148.78125 | E33: =CHOOSE(MATCH(Inputs!B3,{"Worst","Expected","Best"},0),E32*Inputs!B39,E32*Inputs!C39,E32*Inputs!D39) -> 171.09844 | F33: =CHOOSE(MATCH(Inputs!B3,{"Worst","Expected","Best"},0),F32*Inputs!B39,F32*Inputs!C39,F32*Inputs!D39) -> 196.7632 | G33: =CHOOSE(MATCH(Inputs!B3,{"Worst","Expected","Best"},0),G32*Inputs!B39,G32*Inputs!C39,G32*Inputs!D39) -> 226.27768 | H33: =CHOOSE(MATCH(Inputs!B3,{"Worst","Expected","Best"},0),H32*Inputs!B39,H32*Inputs!C39,H32*Inputs!D39) -> 260.21934 | I33: =CHOOSE(MATCH(Inputs!B3,{"Worst","Expected","Best"},0),I32*Inputs!B39,I32*Inputs!C39,I32*Inputs!D39) -> 299.25224 | J33: =CHOOSE(MATCH(Inputs!B3,{"Worst","Expected","Best"},0),J32*Inputs!B39,J32*Inputs!C39,J32*Inputs!D39) -> 344.14007 | K33: =CHOOSE(MATCH(Inputs!B3,{"Worst","Expected","Best"},0),K32*Inputs!B39,K32*Inputs!C39,K32*Inputs!D39) -> 395.76108 | L33: =CHOOSE(MATCH(Inputs!B3,{"Worst","Expected","Best"},0),L32*Inputs!B39,L32*Inputs!C39,L32*Inputs!D39) -> 455.12525 | M33: =CHOOSE(MATCH(Inputs!B3,{"Worst","Expected","Best"},0),M32*Inputs!B39,M32*Inputs!C39,M32*Inputs!D39) -> 523.39403 | N33: =SUM(B33:M33) -> 3262.6876

Sheet Output
A1: TutorLink — Growth Projection Output
A3: Active scenario: | B3: =Inputs!B3 -> Expected
A5: Metric | B5: May | C5: Jun | D5: Jul | E5: Aug | F5: Sep | G5: Oct | H5: Nov | I5: Dec | J5: Jan | K5: Feb | L5: Mar | M5: Apr | N5: 12-Mo Total
A6: =Calculations!A29 -> Total new users (all channels) | B6: =Calculations!B29 -> 67.2 | C6: =Calculations!C29 -> 72.66 | D6: =Calculations!D29 -> 78.693 | E6: =Calculations!E29 -> 85.37115 | F6: =Calculations!F29 -> 92.776583 | G6: =Calculations!G29 -> 101.00285 | H6: =Calculations!H29 -> 110.15659 | ... N6: =Calculations!N29 -> 1337.9556
A7: =Calculations!A30 -> Total net active users | B7: =Calculations!B30 -> 67.2 | C7: =Calculations!C30 -> 139.86 | D7: =Calculations!D30 -> 218.553 | E7: =Calculations!E30 -> 303.92415 | F7: =Calculations!F30 -> 396.70073 | G7: =Calculations!G30 -> 497.70359 | H7: =Calculations!H30 -> 607.86018 | ... N7: =Calculations!N30 -> 1337.9556
A8: =Calculations!A31 -> Total active tutors (scenario) | B8: =Calculations!B31 -> 15 | C8: =Calculations!C31 -> 17.25 | D8: =Calculations!D31 -> 19.8375 | E8: =Calculations!E31 -> 22.813125 | F8: =Calculations!F31 -> 26.235094 | G8: =Calculations!G31 -> 30.170358 | H8: =Calculations!H31 -> 34.695911 | ... N8: =Calculations!N31 -> 69.785871
A9: =Calculations!A32 -> Tutors on paid plan | B9: =Calculations!B32 -> 3.75 | C9: =Calculations!C32 -> 4.3125 | D9: =Calculations!D32 -> 4.959375 | E9: =Calculations!E32 -> 5.7032812 | F9: =Calculations!F32 -> 6.5587734 | G9: =Calculations!G32 -> 7.5425895 | H9: =Calculations!H32 -> 8.6739779 | ... N9: =Calculations!N32 -> 17.446468
A10: =Calculations!A33 -> Monthly revenue (GEL) | B10: =Calculations!B33 -> 112.5 | C10: =Calculations!C33 -> 129.375 | D10: =Calculations!D33 -> 148.78125 | E10: =Calculations!E33 -> 171.09844 | F10: =Calculations!F33 -> 196.7632 | G10: =Calculations!G33 -> 226.27768 | H10: =Calculations!H33 -> 260.21934 | ... N10: =Calculations!N33 -> 3262.6876
A13: Unit Economics Summary
A14: Metric | B14: Worst | C14: Expected | D14: Best
A15: Tutor plan ARPU (GEL/mo) | B15: =Inputs!B39 -> 15 | C15: =Inputs!C39 -> 30 | D15: =Inputs!D39 -> 50
A16: Gross margin (%) | B16: =Inputs!B8 -> 0.8 | C16: =Inputs!C8 -> 0 | D16: =Inputs!D8 -> 0
A17: Avg customer lifetime (months) | B17: =Inputs!B9 -> 18 | C17: =Inputs!C9 -> 0 | D17: =Inputs!D9 -> 0
A18: LTV — tutor (GEL) | B18: =Inputs!B39*Inputs!B8*Inputs!B9 -> 216 | C18: =Inputs!C39*Inputs!C8*Inputs!C9 -> 0 | D18: =Inputs!D39*Inputs!D8*Inputs!D9 -> 0
A19: Blended CAC (GEL) | B19: =AVERAGE(Inputs!B42,Inputs!B43,Inputs!B44) -> 7.6666667 | C19: =AVERAGE(Inputs!C42,Inputs!C43,Inputs!C44) -> 3.3333333 | D19: =AVERAGE(Inputs!D42,Inputs!D43,Inputs!D44) -> 1.1666667
A20: LTV : CAC ratio | B20: =IF(AVERAGE(Inputs!B42,Inputs!B43,Inputs!B44)=0,"-",B18/AVERAGE(Inputs!B42,Inputs!B43,Inputs!B44)&":1") -> 28.1739130434783:1 | C20: =IF(AVERAGE(Inputs!C42,Inputs!C43,Inputs!C44)=0,"-",C18/AVERAGE(Inputs!C42,Inputs!C43,Inputs!C44)&":1") -> 0:1 | D20: =IF(AVERAGE(Inputs!D42,Inputs!D43,Inputs!D44)=0,"-",D18/AVERAGE(Inputs!D42,Inputs!D43,Inputs!D44)&":1") -> 0:1
A21: Payback period (months) | B21: =IF(Inputs!B39*Inputs!B8=0,"-",TEXT(AVERAGE(Inputs!B42,Inputs!B43,Inputs!B44)/(Inputs!B39*Inputs!B8),"0.0")&" mo") -> 0.6 mo | C21: =IF(Inputs!C39*Inputs!C8=0,"-",TEXT(AVERAGE(Inputs!C42,Inputs!C43,Inputs!C44)/(Inputs!C39*Inputs!C8),"0.0")&" mo") -> - | D21: =IF(Inputs!D39*Inputs!D8=0,"-",TEXT(AVERAGE(Inputs!D42,Inputs!D43,Inputs!D44)/(Inputs!D39*Inputs!D8),"0.0")&" mo") -> -
A24: Cumulative Net Active Users — 12-Month Projection
